tests/__init__.py
tests/collective_test.py
tests/geometry_test.py
tests/interpolate_test.py
tests/socialcontext_test.py
tests/trajectories/__init__.py
tests/trajectories/test_concatenate.py
tests/trajectories/test_trajectories.py
tests/trajectories/test_trajectories2.py
trajectorytools/__init__.py
trajectorytools/collective.py
trajectorytools/constants.py
trajectorytools/geometry.py
trajectorytools/interpolate.py
trajectorytools/animation/__init__.py
trajectorytools/animation/animation.py
trajectorytools/animation/plotter.py
trajectorytools/animation/scatter.py
trajectorytools/data/test_trajectories.npy
trajectorytools/data/test_trajectories_idtrackerai.npy
trajectorytools/data/test_trajectories_idtrackerai_with_border.npy
trajectorytools/data/trajectories_with_points.npy
trajectorytools/fish_bouts/__init__.py
trajectorytools/fish_bouts/fish_bouts.py
trajectorytools/plot/__init__.py
trajectorytools/plot/plot.py
trajectorytools/plot/polar.py
trajectorytools/socialcontext/__init__.py
trajectorytools/socialcontext/leadership.py
trajectorytools/socialcontext/socialcontext.py
trajectorytools/trajectories/__init__.py
trajectorytools/trajectories/concatenate.py
trajectorytools/trajectories/trajectories.py
trajectorytools_shaliulab-0.3.6.dist-info/COPYING
trajectorytools_shaliulab-0.3.6.dist-info/METADATA
trajectorytools_shaliulab-0.3.6.dist-info/WHEEL
trajectorytools_shaliulab-0.3.6.dist-info/top_level.txt
trajectorytools_shaliulab-0.3.6.dist-info/RECORD
