Metadata-Version: 2.1
Name: trajectorytools-shaliulab
Version: 0.3.6
Summary: A tool to study 2D trajectories
Home-page: http://github.com/fjhheras/trajectorytools
Author: Francisco J.H. Heras, Francisco Romero Ferrero, Antonio Ortega, Gonzalo G. de Polavieja
Author-email: fjhheras@gmail.com, antonio.ortega@kuleuven.be
License: GPL
Classifier: License :: OSI Approved :: GNU General Public License v3 (GPLv3)
Classifier: Programming Language :: Python
Classifier: Topic :: Scientific/Engineering
Classifier: Topic :: Scientific/Engineering :: Physics
Classifier: Topic :: Software Development :: Libraries
Classifier: Topic :: Utilities
License-File: COPYING
Requires-Dist: MiniballCpp
Requires-Dist: matplotlib
Requires-Dist: scikit-learn
Requires-Dist: scipy
